shadow3-23.9.19.dist-info/WHEEL
shadow3-23.9.19.dist-info/top_level.txt
shadow3-23.9.19.dist-info/RECORD
shadow3-23.9.19.dist-info/METADATA
shadow3-23.9.19.dist-info/LICENSE
shadow3.libs/libquadmath-96973f99.so.0.0.0
shadow3.libs/libgfortran-040039e1.so.5.0.0
Shadow/__init__.py
Shadow/ShadowToolsPrivate.py
Shadow/ShadowTools.py
Shadow/ShadowLib.cpython-39-x86_64-linux-gnu.so
Shadow/ShadowPreprocessorsXraylib.py
Shadow/ShadowLibExtensions.py
