Metadata-Version: 2.1
Name: shadow3
Version: 23.9.19
Summary: SHADOW is an open source ray tracing code for modeling optical systems.
Home-page: http://github.com/oasys-kit/shadow3
Author: Franco Cerrina and Manuel Sanchez del Rio
Author-email: srio@esrf.eu
License: http://www.gnu.org/licenses/gpl-3.0.html
Platform: UNKNOWN
License-File: LICENSE
Requires-Dist: numpy
